restclients_core/VERSION
restclients_core/__init__.py
restclients_core/cache.py
restclients_core/dao.py
restclients_core/exceptions.py
restclients_core/test.py
restclients_core/thread.py
restclients_core/models/__init__.py
restclients_core/models/fields.py
restclients_core/tests/__init__.py
restclients_core/tests/test_local_cache.py
restclients_core/tests/test_prometheus.py
restclients_core/tests/test_thread.py
restclients_core/tests/test_timing_log.py
restclients_core/tests/dao_implementation/__init__.py
restclients_core/tests/dao_implementation/test_backend.py
restclients_core/tests/dao_implementation/test_live.py
restclients_core/tests/dao_implementation/test_mock.py
restclients_core/tests/dao_implementation/resource_override/testing/file/override.json
restclients_core/tests/dao_implementation/resources/testing/file/found.json
restclients_core/tests/dao_implementation/resources/testing/file/image.jpg
restclients_core/tests/dao_implementation/resources/testing/file/override.json
restclients_core/tests/dao_implementation/resources/testing/file/search_first_a_second_b
restclients_core/tests/dao_implementation/resources/testing/file/search_first_a_second_b.POST
restclients_core/tests/dao_implementation/resources/testing/file/search_first_abc.http-headers
restclients_core/tests/dao_implementation/resources/testing/file/search_fourth_d_third_c_second_b_first_a
restclients_core/tests/dao_implementation/resources/testing/file/search_fourth_d_third_c_second_b_first_a.http-headers
restclients_core/tests/dao_implementation/resources/testing/file/search_second_a_b_c_first_a
restclients_core/tests/dao_implementation/resources/testing/file/search_second_b_first_a
restclients_core/tests/dao_implementation/resources/testing/file/with_headers.json
restclients_core/tests/dao_implementation/resources/testing/file/with_headers.json.http-headers
restclients_core/tests/dao_implementation/resources/testing/file/with_only_headers.json
UW_RestClients_Core-1.4.3.dist-info/LICENSE
UW_RestClients_Core-1.4.3.dist-info/METADATA
UW_RestClients_Core-1.4.3.dist-info/WHEEL
UW_RestClients_Core-1.4.3.dist-info/top_level.txt
UW_RestClients_Core-1.4.3.dist-info/RECORD
