Metadata-Version: 2.1
Name: UW-RestClients-Core
Version: 1.4.3
Summary: Core code for clients of a variety of RESTful web services at the University of Washington
Home-page: https://github.com/uw-it-aca/uw-restclients-core
Author: UW-IT T&LS
Author-email: aca-it@uw.edu
License: Apache License, Version 2.0
Classifier: Intended Audience :: Developers
Classifier: License :: OSI Approved :: Apache Software License
Classifier: Operating System :: OS Independent
Classifier: Programming Language :: Python
License-File: LICENSE
Requires-Dist: commonconf
Requires-Dist: urllib3
Requires-Dist: python-dateutil
Requires-Dist: prometheus-client
Requires-Dist: mock
